django_auth_recovery_codes
