Metadata-Version: 2.4
Name: django-auth-recovery-codes
Version: 1.0.3
Summary: Django app for 2FA recovery codes
Home-page: https://github.com/EgbieAndersonUku1/django_2fa_recovery_codes
Author: Egbie Uku
Author-email: egbieuku@hotmail.com
License: MIT
Requires-Python: >=3.10,<3.14
License-File: LICENSE
Requires-Dist: Django>=5.0
Requires-Dist: django-picklefield>=3.3
Requires-Dist: django-q2>=1.8.0
Requires-Dist: django-email-sender>=2.0.6
Requires-Dist: requests>=2.32
Requires-Dist: reportlab>=4.4
Requires-Dist: redis>=3.5
Requires-Dist: pillow>=11.0
Requires-Dist: arrow>=1.3
Requires-Dist: beautifulsoup4>=4.13
Requires-Dist: asgiref>=3.9
Requires-Dist: soupsieve>=2.7
Requires-Dist: sqlparse>=0.5
Requires-Dist: typing_extensions>=4.14
Requires-Dist: tzdata>=2025.2
Provides-Extra: dev
Requires-Dist: black; extra == "dev"
Requires-Dist: flake8; extra == "dev"
Requires-Dist: pytest; extra == "dev"
Requires-Dist: types-python-dateutil; extra == "dev"
Dynamic: author
Dynamic: author-email
Dynamic: home-page
Dynamic: license-file
Dynamic: requires-python
